qappuccino/__init__.py
qappuccino/qappuccino.resource
qappuccino/qappuccinoSteps/LPS-API.resource
qappuccino/qappuccinoSteps/LPS-BrowserControl.resource
qappuccino/qappuccinoSteps/LPS-BuiltIn.resource
qappuccino/qappuccinoSteps/LPS-Checks.resource
qappuccino/qappuccinoSteps/LPS-Clicks.resource
qappuccino/qappuccinoSteps/LPS-Collections.resource
qappuccino/qappuccinoSteps/LPS-DatabaseLibrary.resource
qappuccino/qappuccinoSteps/LPS-DateTime.resource
qappuccino/qappuccinoSteps/LPS-Dialogs.resource
qappuccino/qappuccinoSteps/LPS-Inputs.resource
qappuccino/qappuccinoSteps/LPS-JSONLibrary.resource
qappuccino/qappuccinoSteps/LPS-OperatingSystem.resource
qappuccino/qappuccinoSteps/LPS-Process.resource
qappuccino/qappuccinoSteps/LPS-Request.resource
qappuccino/qappuccinoSteps/LPS-SeleniumBrowserControl.resource
qappuccino/qappuccinoSteps/LPS-SeleniumChecks.resource
qappuccino/qappuccinoSteps/LPS-SeleniumClicks.resource
qappuccino/qappuccinoSteps/LPS-SeleniumInputs.resource
qappuccino/qappuccinoSteps/LPS-SeleniumWaits.resource
qappuccino/qappuccinoSteps/LPS-SelfHealingSteps.resource
qappuccino/qappuccinoSteps/LPS-String.resource
qappuccino/qappuccinoSteps/LPS-TimestampsSreenshots.resource
qappuccino/qappuccinoSteps/LPS-Waits.resource
qappuccino/qappuccinoSteps/LPS-XML.resource
qappuccino/qappuccinoSteps/__init__.py
qappuccino/qappuccinoSteps/settings.resource
qappuccinolibrary-0.1.28.dist-info/METADATA
qappuccinolibrary-0.1.28.dist-info/WHEEL
qappuccinolibrary-0.1.28.dist-info/top_level.txt
qappuccinolibrary-0.1.28.dist-info/RECORD
